aws_teams_logger/__init__.py
aws_teams_logger/__version__.py
aws_teams_logger/constants.py
aws_teams_logger/log.py
aws_teams_logger/models.py
aws_teams_logger/loggers/__init__.py
aws_teams_logger/loggers/base_logger.py
aws_teams_logger/loggers/globals.py
aws_teams_logger/loggers/lambda_logger.py
aws_teams_logger/loggers/task_logger.py
aws_teams_logger/utils/__init__.py
aws_teams_logger/utils/date_util.py
aws_teams_logger/utils/decorators.py
aws_teams_logger/utils/split.py
aws_teams_logger/utils/time_util.py
aws_teams_logger/utils/types.py
aws_teams_logger/utils/aws/__init__.py
aws_teams_logger/utils/aws/client_cache.py
aws_teams_logger/utils/aws/ses/__init__.py
aws_teams_logger/utils/aws/ses/models.py
aws_teams_logger/utils/aws/ses/ses.py
aws_teams_logger/utils/aws/ses/templates/__init__.py
aws_teams_logger/utils/aws/ses/templates/delete.py
aws_teams_logger/utils/aws/ses/templates/upload.py
aws_teams_logger/utils/aws/ses/templates/utils.py
aws_teams_logger/utils/aws/ses/templates/send_to_outlook/__init__.py
aws_teams_logger/utils/aws/ses/templates/send_to_outlook/body.html
aws_teams_logger/utils/aws/ses/templates/send_to_outlook/template.py
aws_teams_logger/utils/aws/ses/templates/send_to_teams/__init__.py
aws_teams_logger/utils/aws/ses/templates/send_to_teams/body.html
aws_teams_logger/utils/aws/ses/templates/send_to_teams/template.py
aws_teams_logger-0.7.1.dist-info/LICENSE
aws_teams_logger-0.7.1.dist-info/METADATA
aws_teams_logger-0.7.1.dist-info/WHEEL
aws_teams_logger-0.7.1.dist-info/top_level.txt
aws_teams_logger-0.7.1.dist-info/RECORD
