Metadata-Version: 2.1
Name: aws-teams-logger
Version: 0.7.1
Summary: Python MS Teams and Email logger for AWS environments
Home-page: https://github.com/rnag/aws-teams-logger
Author: Ritvik Nag
Author-email: rv.kvetch@gmail.com
License: MIT
Keywords: teams logger,ms-teams-logger,microsoft teams,ms-teams,teams logger for AWS,aws-lambda,ecs,fargate
Platform: UNKNOWN
Classifier: Development Status :: 5 - Production/Stable
Classifier: Intended Audience :: Developers
Classifier: Topic :: System :: Logging
Classifier: Topic :: Communications :: Chat
Classifier: License :: OSI Approved :: MIT License
Classifier: Programming Language :: Python :: 3
Classifier: Programming Language :: Python :: 3.7
Classifier: Programming Language :: Python :: 3.8
Classifier: Programming Language :: Python :: 3.9
Classifier: Programming Language :: Python :: 3.10
Requires-Python: >=3.7
Requires-Dist: pytz (<2022.0,>=2018.1)
Requires-Dist: requests
Provides-Extra: standalone
Requires-Dist: boto3 (~=1.17.85) ; extra == 'standalone'
